django_onivoro-0.1.2.dist-info/DESCRIPTION.rst
django_onivoro-0.1.2.dist-info/METADATA
django_onivoro-0.1.2.dist-info/RECORD
django_onivoro-0.1.2.dist-info/WHEEL
django_onivoro-0.1.2.dist-info/metadata.json
django_onivoro-0.1.2.dist-info/top_level.txt
onivoro/__init__.py
onivoro/apps.py
onivoro/choices.py
onivoro/exceptions.py
onivoro/forms.py
onivoro/models.py
onivoro/ogr_utils.py
onivoro/settings.py
onivoro/signals.py
onivoro/sincronizador.py
onivoro/urls.py
onivoro/views.py
onivoro/management/__init__.py
onivoro/management/commands/__init__.py
onivoro/management/commands/sync_external.py
onivoro/migrations/0001_initial.py
onivoro/migrations/__init__.py
onivoro/templates/onivoro/base.html
onivoro/templates/onivoro/confirmacao_excluir.html
onivoro/templates/onivoro/detalhe.html
onivoro/templates/onivoro/email_falha.txt
onivoro/templates/onivoro/email_sucesso.txt
onivoro/templates/onivoro/fonte_externa_simples.html
onivoro/templates/onivoro/home.html
onivoro/templates/onivoro/sincronizado.html
